setup.cfg
setup.py
bin/ec2
heisenberg/__init__.py
heisenberg/interface.py
heisenberg/utils.py
heisenberg/command/__init__.py
heisenberg/command/base.py
heisenberg/command/find.py
heisenberg/command/ssh.py
heisenberg_ec2.egg-info/PKG-INFO
heisenberg_ec2.egg-info/SOURCES.txt
heisenberg_ec2.egg-info/dependency_links.txt
heisenberg_ec2.egg-info/not-zip-safe
heisenberg_ec2.egg-info/requires.txt
heisenberg_ec2.egg-info/top_level.txt