Metadata-Version: 1.1
Name: heisenberg-ec2
Version: 1.0.2
Summary: A utility for searching and connecting to EC2 instances with caching for quicker interaction
Home-page: https://github.com/adampetrovic/heisenberg
Author: Adam Petrovic
Author-email: adam@petrovic.com.au
License: UNKNOWN
Download-URL: https://github.com/adampetrovic/heisenberg/tarball/1.0.2
Keywords: heisenberg
Platform: UNKNOWN
Classifier: Development Status :: 2 - Pre-Alpha
Classifier: Intended Audience :: Developers
Classifier: License :: OSI Approved :: BSD License
Classifier: Natural Language :: English
Classifier: Programming Language :: Python :: 2
Classifier: Programming Language :: Python :: 2.6
Classifier: Programming Language :: Python :: 2.7
